{
  "id": "LOCAL-GENERIC-FUNCTOR-INTERFACE-CONVENIENCE-LAWS",
  "title": "Add convenience lemmas for map-id/compose congruence",
  "description": "Add map-id and compose convenience lemmas so reasoning about the interface stays manageable.",
  "status": "done",
  "category": "Infrastructure",
  "source": "DefinitionDictionary",
  "files": [
    "src/agda/Infrastructure/Functor/Interface.agda"
  ],
  "tags": [
    "Functor",
    "Interface",
    "Law"
  ],
  "dependsOn": [
    "LOCAL-GENERIC-FUNCTOR-INTERFACE-COMPLETENESS"
  ],
  "provenance": [
    "intake/codex_handoff.md"
  ],
  "related": []
}