{
  "id": "GP-Gp822",
  "title": "GP822: The Fractal Manifest (v22.0)",
  "description": "GP822: The Fractal Manifest (v22.0). Source: Plan/CIM/IngestedRoadmaps/Analysis.agda. Category: IngestedGP. Tags: GP. Affects: Implementation.agda",
  "status": "not-started",
  "category": "IngestedGP",
  "source": "Plan/CIM/IngestedRoadmaps/Analysis.agda",
  "files": [
    "src/agda/Plan/CIM/Implementation.agda"
  ],
  "tags": [
    "GP"
  ],
  "dependsOn": [],
  "provenance": [
    "GP-Gp822|Plan/CIM/IngestedRoadmaps/Analysis.agda",
    "ROADMAP-MD-26|ROADMAP.md"
  ],
  "related": []
}