{
  "id": "GP-Gp500",
  "title": "GP500: Dimensional Relief",
  "description": "GP500: Dimensional Relief. Source: Plan/CIM/IngestedRoadmaps/Corrections.agda. Category: IngestedGP. Tags: GP. Affects: Implementation.agda",
  "status": "not-started",
  "category": "IngestedGP",
  "source": "Plan/CIM/IngestedRoadmaps/Corrections.agda",
  "files": [
    "src/agda/Plan/CIM/Implementation.agda"
  ],
  "tags": [
    "GP"
  ],
  "dependsOn": [],
  "provenance": [
    "GP-Gp500|Plan/CIM/IngestedRoadmaps/Corrections.agda",
    "ROADMAP-MD-2|ROADMAP.md"
  ],
  "related": [],
  "intent": "Implement GP500: Dimensional Relief as specified.",
  "deliverable": "Compiled Agda modules: Implementation.agda",
  "scope": {
    "in": [],
    "out": []
  },
  "acceptance": [
    "All Agda modules compile without errors",
    "Code review and integration approval"
  ],
  "evidence": [],
  "derivedTags": [
    "GP"
  ],
  "moduleAnchors": [
    "Plan.CIM.Implementation"
  ],
  "complexity": "low",
  "inputs": [],
  "outputs": [
    "Agda modules: Implementation.agda"
  ],
  "suggestedDependencies": [],
  "definitions": [],
  "risks": []
}